{
  "info": {
    "key": "g1059_0317"
  },
  "sheets": {
    "מזומנים": {
      "columns": [
        "שם המנפיק/שם נייר ערך",
        "מספר ני\"ע",
        "מספר מנפיק",
        "דירוג",
        "שם מדרג",
        "סוג מטבע",
        "שיעור ריבית",
        "תשואה לפדיון",
        "שווי שוק",
        "שעור מנכסי אפיק ההשקעה"
      ],
      "data": [
        [
          "לאומי - שקל חדש",
          910001,
          "77 -520000225",
          "AA+IL",
          "מעלות S&P",
          "שקל חדש",
          0.0,
          0,
          9.59,
          0.44
        ],
        [
          "בנק הפועלים - דולר קנדי",
          912140,
          "12 -520000118",
          "AA+IL",
          "מעלות S&P",
          "דולר קנדי",
          0.0,
          0,
          2.65,
          0.12
        ],
        [
          "בנק הפועלים - דולר אמריקאי",
          912019,
          "12 -520000118",
          "AA+IL",
          "מעלות S&P",
          "דולר אמריקאי",
          0.0,
          0,
          252.97,
          11.72
        ],
        [
          "בנק הפועלים - אירו",
          912100,
          "12 -520000118",
          "AA+IL",
          "מעלות S&P",
          "אירו",
          0.0,
          0,
          9.2,
          0.43
        ],
        [
          "בנק הפועלים - לירה שטרלינג",
          912027,
          "12 -520000118",
          "AA+IL",
          "מעלות S&P",
          "לירה שטרלינג",
          0.0,
          0,
          8.84,
          0.41
        ],
        [
          "פועלים סהר - שקל חדש",
          111111222,
          "12 -512199381",
          "AA+IL",
          "מעלות S&P",
          "שקל חדש",
          0.02,
          0,
          1874.37,
          86.87
        ]
      ]
    },
    "תעודות סל": {
      "columns": [
        "שם המנפיק/שם נייר ערך",
        "מספר ני\"ע",
        "זירת מסחר",
        "מספר מנפיק",
        "ענף מסחר",
        "סוג מטבע",
        "ערך נקוב",
        "שער",
        "פדיון/ריבית לקבל",
        "שווי שוק",
        "שעור מערך נקוב מונפק",
        "שעור מנכסי אפיק ההשקעה",
        "שעור מסך נכסי השקעה"
      ],
      "data": [
        [
          "הראל סל יד יתר50",
          1116383,
          "TASE",
          514103811,
          "מניות",
          "שקל חדש",
          50000,
          688.0,
          0,
          344.0,
          0.07,
          1.15,
          1.05
        ],
        [
          "הראלס יא תא75",
          1113745,
          "TASE",
          514103811,
          "מניות",
          "שקל חדש",
          119400,
          1000.0,
          0,
          1194.0,
          0.05,
          4.01,
          3.65
        ],
        [
          "הראל סל ת\"א 25",
          1113703,
          "TASE",
          514103811,
          "מניות",
          "שקל חדש",
          166845,
          1418.0,
          0,
          2365.86,
          0.2,
          7.94,
          7.23
        ],
        [
          "'תכלית ת\"א 25 תעודות סל ב",
          1091826,
          "TASE",
          513594101,
          "מניות",
          "שקל חדש",
          84484,
          1416.0,
          0,
          1196.29,
          0.04,
          4.01,
          3.66
        ],
        [
          "תכלית נאסדק ביוטכנולוגיה",
          1095751,
          "TASE",
          513594101,
          "מניות",
          "שקל חדש",
          344,
          10870.0,
          0,
          37.39,
          0.0,
          0.12,
          0.11
        ],
        [
          "*פסגות סל תל בונד שקלי סד-1",
          1116326,
          "TASE",
          513952457,
          "אג\"ח",
          "שקל חדש",
          220000,
          362.79,
          0,
          798.14,
          0.04,
          2.68,
          2.44
        ],
        [
          "הראל שחר 5-2",
          1113729,
          "TASE",
          514103811,
          "אג\"ח",
          "שקל חדש",
          131887,
          422.57,
          0,
          557.31,
          0.12,
          1.87,
          1.7
        ],
        [
          "*פסגות סל מק\"מ",
          1112879,
          "TASE",
          513952457,
          "אג\"ח",
          "שקל חדש",
          473780,
          277.45,
          0,
          1314.5,
          0.12,
          4.41,
          4.02
        ],
        [
          "*פסגות תל-בונד צמודות יתר",
          1127752,
          "TASE",
          513952457,
          "אג\"ח",
          "שקל חדש",
          23000,
          3315.16,
          0,
          762.49,
          0.1,
          2.56,
          2.33
        ],
        [
          "*פסגות תל בונד תשואות",
          1128529,
          "TASE",
          513952457,
          "אג\"ח",
          "שקל חדש",
          23000,
          3479.8,
          0,
          800.35,
          0.07,
          2.68,
          2.45
        ],
        [
          "*פסגות סל תל בונד 60 סד-1",
          1109420,
          "TASE",
          513952457,
          "אג\"ח",
          "שקל חדש",
          70584,
          3181.33,
          0,
          2245.51,
          0.11,
          7.53,
          6.87
        ],
        [
          "קסם מק\"מ",
          1111665,
          "TASE",
          513502211,
          "אג\"ח",
          "שקל חדש",
          53163,
          2772.95,
          0,
          1474.18,
          0.11,
          4.95,
          4.51
        ],
        [
          "קסם תל בונד 60",
          1109248,
          "TASE",
          513502211,
          "אג\"ח",
          "שקל חדש",
          68100,
          3195.1,
          0,
          2175.86,
          0.05,
          7.3,
          6.65
        ],
        [
          "תכלית (אינדקס) שחר 5+",
          1110790,
          "TASE",
          513801605,
          "אג\"ח",
          "שקל חדש",
          442502,
          609.96,
          0,
          2699.08,
          0.89,
          9.06,
          8.25
        ],
        [
          "תכלית גלילים 10-5",
          1108570,
          "TASE",
          513815258,
          "אג\"ח",
          "שקל חדש",
          71429,
          3533.94,
          0,
          2524.26,
          0.29,
          8.47,
          7.72
        ],
        [
          "AMUNDI ETF EMERGING MAR",
          "FR0010959692",
          "CAC",
          92767,
          "מניות",
          "דולר אמריקאי",
          6500,
          462.8,
          0,
          106.16,
          0.0,
          0.36,
          0.32
        ],
        [
          "ISHARES NASDAQ BIOTECH INDEX",
          "US4642875565",
          "NYSE",
          98339,
          "מניות",
          "דולר אמריקאי",
          32,
          33055.0,
          0,
          37.33,
          0.0,
          0.12,
          0.11
        ],
        [
          "HORIZONS S&P/TSX 60 INDEX ET",
          "CA44049A1241",
          "אחר",
          93169,
          "מניות",
          "דולר קנדי",
          196,
          3181.0,
          0,
          17.64,
          0.0,
          0.06,
          0.05
        ],
        [
          "נאסדאק 100 אינדקס טרקינג סטוק",
          "US73935A1043",
          "NYSE",
          98126,
          "מניות",
          "דולר אמריקאי",
          1400,
          14441.0,
          0,
          713.47,
          0.0,
          2.39,
          2.18
        ],
        [
          "ISHARES PLC - IFTSE 100",
          "IE0005042456",
          "LSE",
          99588,
          "מניות",
          "לירה שטרלינג",
          1156,
          722.8,
          0,
          39.57,
          0.0,
          0.13,
          0.12
        ],
        [
          "LYXOR ETF MSCI EUROPE",
          "FR0010261198",
          "CAC",
          97320,
          "מניות",
          "אירו",
          35,
          12870.0,
          0,
          18.72,
          0.0,
          0.06,
          0.06
        ],
        [
          "DOW JONES STOXX 600 SOURCE",
          "IE00B60SWW18",
          "DAX",
          98262,
          "מניות",
          "אירו",
          2650,
          7807.0,
          0,
          860.0,
          0.0,
          2.88,
          2.63
        ],
        [
          "MSCI EUROPE SOURCE ETF",
          "IE00B60SWY32",
          "DAX",
          98262,
          "מניות",
          "אירו",
          44,
          21165.0,
          0,
          38.71,
          0.0,
          0.13,
          0.12
        ],
        [
          "אס פי די אר טראסט סיריס 1",
          "US78462F1030",
          "NYSE",
          99343,
          "מניות",
          "דולר אמריקאי",
          2831,
          25035.0,
          0,
          2501.15,
          0.0,
          8.39,
          7.65
        ],
        [
          "ואנגארד אימרג' מרקט וייפרס",
          "US9220428588",
          "NYSE",
          99237,
          "מניות",
          "דולר אמריקאי",
          4519,
          4313.0,
          0,
          687.82,
          0.0,
          2.31,
          2.1
        ],
        [
          "VANGUARD FTSE 100 ETF",
          "IE00B810Q511",
          "אחר",
          99237,
          "מניות",
          "לירה שטרלינג",
          1700,
          3243.0,
          0,
          261.08,
          0.0,
          0.88,
          0.8
        ],
        [
          "WIDSOMTREE JAPAN DIVIDEND",
          "US97717W8516",
          "אחר",
          99939,
          "מניות",
          "דולר אמריקאי",
          2760,
          5478.0,
          0,
          533.56,
          0.0,
          1.79,
          1.63
        ],
        [
          "WISDOMTREE GERMANY HEDGED EQ",
          "US97717W4481",
          "NASDAQ",
          99939,
          "מניות",
          "דולר אמריקאי",
          2147,
          3128.0,
          0,
          237.0,
          0.0,
          0.79,
          0.72
        ],
        [
          "ISHARES GLOBAL HIGH YIELD BD",
          "IE00B74DQ490",
          "LSE",
          98339,
          "אג\"ח",
          "דולר אמריקאי",
          2100,
          9898.0,
          0,
          733.53,
          0.0,
          2.46,
          2.24
        ],
        [
          "ISHARES USD CORPORATE BOND",
          "IE0032895942",
          "LSE",
          99342,
          "אג\"ח",
          "דולר אמריקאי",
          6186,
          11594.0,
          0,
          2531.02,
          0.0,
          8.49,
          7.74
        ]
      ]
    },
    "קרנות נאמנות": {
      "columns": [
        "שם המנפיק/שם נייר ערך",
        "מספר ני\"ע",
        "זירת מסחר",
        "מספר מנפיק",
        "ענף מסחר",
        "דירוג",
        "שם מדרג",
        "סוג מטבע",
        "ערך נקוב",
        "שער",
        "שווי שוק",
        "שעור מערך נקוב מונפק",
        "שעור מנכסי אפיק ההשקעה",
        "שעור מסך נכסי השקעה"
      ],
      "data": [
        [
          "AB FCP I-AMER INC-S1 USD",
          "LU0231611681",
          "אחר",
          93004,
          "Fixed Income",
          "ללא דירוג",
          "ללא דירוג",
          "דולר אמריקאי",
          2801,
          2084,
          206,
          0,
          100,
          0.63
        ]
      ]
    },
    "לא סחיר - אג\"ח קונצרני": {
      "columns": [
        "שם המנפיק/שם נייר ערך",
        "מספר ני\"ע",
        "ספק המידע",
        "מספר מנפיק",
        "ענף מסחר",
        "דירוג",
        "שם מדרג",
        "תאריך רכישה",
        "מח\"מ",
        "סוג מטבע",
        "שיעור ריבית",
        "תשואה לפדיון",
        "ערך נקוב",
        "שער",
        "שווי הוגן",
        "שעור מערך נקוב מונפק",
        "שעור מנכסי אפיק ההשקעה",
        "שעור מסך נכסי השקעה"
      ],
      "data": [
        [
          "מ - 'נתיבי גז אג\"ח א",
          1103084,
          "",
          513436394,
          "שרותים",
          "AAIL",
          "מעלות S&P",
          "2007-01-02",
          4.87,
          "שקל חדש",
          5.6,
          0.78,
          21519.35,
          151.51,
          32.6,
          0.0,
          76.9,
          0.1
        ],
        [
          "אולימפיה אג\"ח ג' ז\"פ 2015.8.31",
          1790062,
          "",
          520035155,
          "נדל\"ן ובינוי",
          "ללא דירוג",
          "ללא דירוג",
          "2007-05-20",
          2.35,
          "שקל חדש",
          5.9,
          0.0,
          11023.21,
          2.0,
          0.22,
          0.01,
          0.52,
          0.0
        ],
        [
          ". אייס אוטו אגח א",
          1107531,
          "",
          511739294,
          "השקעה ואחזקות",
          "ללא דירוג",
          "ללא דירוג",
          "2007-11-14",
          1.27,
          "שקל חדש",
          6.1,
          0.0,
          4114.96,
          226.25,
          9.31,
          0.0,
          21.96,
          0.03
        ],
        [
          "דוראה אג\"ח ב' ז\"פ 2014.4.30",
          3720075,
          "",
          520038282,
          "נדל\"ן ובינוי",
          "ללא דירוג",
          "ללא דירוג",
          "2006-05-17",
          1.44,
          "שקל חדש",
          4.9,
          0.0,
          1102.5,
          9.0,
          0.1,
          0.0,
          0.23,
          0.0
        ],
        [
          "דוראה אגח ד ז\"פ 2015.2.28",
          3720117,
          "",
          520038282,
          "נדל\"ן ובינוי",
          "ללא דירוג",
          "ללא דירוג",
          "2007-05-24",
          2.27,
          "שקל חדש",
          5.15,
          0.0,
          1837.5,
          9.0,
          0.16,
          0.0,
          0.39,
          0.0
        ],
        [
          "יורו טרייד נדל\"ן אגח א' זפ 2013.1.31",
          1101054,
          "",
          513880666,
          "נדל\"ן ובינוי",
          "ללא דירוג",
          "ללא דירוג",
          "2007-01-28",
          0.42,
          "שקל חדש",
          7.5,
          0.0,
          350529.0,
          0.0,
          0.0,
          0.61,
          0.0,
          0.0
        ]
      ]
    },
    "לא סחיר - חוזים עתידיים": {
      "columns": [
        "שם המנפיק/שם נייר ערך",
        "מספר ני\"ע",
        "ענף מסחר",
        "סוג מטבע",
        "תאריך רכישה",
        "ערך נקוב",
        "שער",
        "שווי הוגן",
        "שעור מנכסי אפיק ההשקעה",
        "שעור מסך נכסי השקעה"
      ],
      "data": [
        [
          "חוזה עתידי forward 14/12/17",
          9126434659,
          "ל.ר",
          "שקל חדש",
          "2017-03-15",
          -1110000,
          -10.01,
          111.17,
          133.42,
          0.34
        ],
        [
          "חוזה עתידי forward 20/12/17",
          9126441449,
          "ל.ר",
          "שקל חדש",
          "2017-03-23",
          -130000,
          21.42,
          -27.85,
          -33.42,
          -0.08
        ]
      ]
    },
    "הלוואות": {
      "columns": [
        "שם נייר ערך",
        "קונסורציום כן/לא",
        "מספר נייר",
        "מספר מנפיק",
        "דירוג",
        "תאריך רכישה",
        "שם מדרג",
        "מח\"מ",
        "סוג מטבע",
        "שעור ריבית ממוצע",
        "תשואה לפדיון",
        "ערך נקוב",
        "שער",
        "שווי הוגן",
        "שעור מנכסי אפיק ההשקעה",
        "שעור מסך נכסי השקעה"
      ],
      "data": [
        [
          "הלוואות פסגות שיא השתלמות מדדים כללי",
          "לא",
          800063976,
          513765347,
          "AA+",
          "2013-12-05",
          "פנימי",
          1.9,
          "שקל חדש",
          0,
          0.74,
          403548.01,
          100.23,
          404.48,
          100,
          1.24
        ]
      ]
    }
  }
}