{
  "info": {
    "key": "g7231_0317"
  },
  "sheets": {
    "מזומנים": {
      "columns": [
        "שם המנפיק/שם נייר ערך",
        "מספר ני\"ע",
        "מספר מנפיק",
        "דירוג",
        "שם מדרג",
        "סוג מטבע",
        "שיעור ריבית",
        "תשואה לפידיון",
        "שווי שוק",
        "שעור מנכסי אפיק ההשקעה",
        "שעור מסך נכסי השקעה"
      ],
      "data": [
        [
          "עו'ש- לאומי",
          "1111111111- 10",
          10,
          "AAA",
          "מעלות",
          "שקל חדש",
          0,
          0,
          294.72724,
          96.3,
          5.78
        ],
        [
          "דולר- לאומי",
          "20001- 10",
          10,
          "AAA",
          "מעלות",
          "דולר אמריקאי",
          0,
          0,
          11.33415988,
          3.7,
          0.22
        ]
      ]
    },
    "תעודות התחייבות ממשלתיות": {
      "columns": [
        "שם המנפיק/שם נייר ערך",
        "מספר ני\"ע",
        "זירת מסחר",
        "דירוג",
        "שם מדרג",
        "תאריך רכישה",
        "מח\"מ",
        "סוג מטבע",
        "שיעור ריבית",
        "תשואה לפידיון",
        "ערך נקוב",
        "שער",
        "שווי שוק",
        "שעור מערך נקוב**** מונפק",
        "שעור מנכסי אפיק ההשקעה",
        "שעור מסך נכסי השקעה"
      ],
      "data": [
        [
          "גליל 5903- גליל",
          9590332,
          "TASE",
          "RF",
          "פנימי",
          "16/11/16",
          3.62,
          "שקל חדש",
          4.0,
          -0.06,
          59000,
          150.27,
          88.6593,
          0,
          18.16,
          1.74
        ],
        [
          "ממשלתי צמוד 1020- גליל",
          1137181,
          "TASE",
          "RF",
          "פנימי",
          "05/12/16",
          3.07,
          "שקל חדש",
          0.1,
          -0.12,
          155000,
          100.68,
          156.054,
          0,
          31.97,
          3.06
        ],
        [
          "ממשלתי צמודה 0536- גליל",
          1097708,
          "TASE",
          "RF",
          "פנימי",
          "19/03/15",
          14.46,
          "שקל חדש",
          4.0,
          0.96,
          30000,
          180.38,
          54.114,
          0,
          11.09,
          1.06
        ],
        [
          "ממשלתי צמודה 922- גליל",
          1124056,
          "TASE",
          "RF",
          "פנימי",
          "02/11/15",
          4.76,
          "שקל חדש",
          2.75,
          -0.09,
          25000,
          117.27,
          29.3175,
          0,
          6.01,
          0.57
        ],
        [
          "ממשל שקלית 120- שחר",
          1115773,
          "TASE",
          "RF",
          "פנימי",
          "16/08/17",
          2.2,
          "שקל חדש",
          5.0,
          0.22,
          75000,
          114.45,
          85.8375,
          0,
          17.59,
          1.68
        ],
        [
          "Israel 5.125 3/19- ממשל דואלית",
          "US46513E5Y48",
          "אחר",
          "A+",
          "S&P",
          "09/12/14",
          1.45,
          "דולר אמריקאי",
          5.13,
          1.72,
          20000,
          105.048472,
          74.1432115376,
          0,
          15.19,
          1.45
        ]
      ]
    },
    "אג\"ח קונצרני": {
      "columns": [
        "שם המנפיק/שם נייר ערך",
        "מספר ני\"ע",
        "זירת מסחר",
        "ספק מידע",
        "מספר מנפיק",
        "ענף מסחר",
        "דירוג",
        "שם מדרג",
        "תאריך רכישה",
        "מח\"מ",
        "סוג מטבע",
        "שיעור ריבית",
        "תשואה לפידיון",
        "ערך נקוב",
        "שער",
        "פדיון/ ריבית לקבל",
        "שווי שוק",
        "שעור מערך נקוב מונפק",
        "שעור מנכסי אפיק ההשקעה",
        "שעור מסך נכסי השקעה"
      ],
      "data": [
        [
          "חשמל אגח 27- חברת החשמל לישראל בע\"מ",
          6000210,
          "TASE",
          "אחר",
          520000472,
          "חיפושי נפט וגז",
          "AA",
          "מעלות",
          "30/08/16",
          8.68,
          "שקל חדש",
          3.85,
          1.68,
          39600.0,
          119.69,
          0.7623,
          48.15954,
          0.0,
          2.63,
          0.94
        ],
        [
          "נורסטאר  אגח יא- נורסטאר החזקות אינק  לשעבר גזית אינק",
          7230352,
          "TASE",
          "אחר",
          723,
          "נדל\"ן ובינוי",
          "A+",
          "מעלות",
          "30/04/17",
          5.43,
          "שקל חדש",
          3.0,
          2.68,
          50000.0,
          102.16,
          0.75226,
          51.83226,
          0.02,
          2.84,
          1.02
        ],
        [
          "דיסקונט שה 1-הפך סחיר - בנק דיסקונט לישראל בע\"מ",
          6910095,
          "TASE",
          "אחר",
          520007030,
          "בנקים",
          "A",
          "מעלות",
          "05/05/16",
          3.89,
          "שקל חדש",
          5.1,
          1.12,
          40000.0,
          139.35,
          0.61003,
          56.35003,
          0.0,
          3.08,
          1.1
        ],
        [
          "יוניברסל  אגח א- יוניברסל מוטורס  ישראל בע\"מ",
          1141639,
          "TASE",
          "אחר",
          511809071,
          "מסחר",
          "A",
          "מעלות",
          "10/09/17",
          2.86,
          "שקל חדש",
          2.65,
          1.77,
          63125.0,
          102.11,
          0.0,
          64.4569375,
          0.01,
          3.53,
          1.26
        ],
        [
          "אינטרנט זהב אגח ד- אינטרנט גולד - קווי זהב בע\"מ",
          1131614,
          "TASE",
          "אחר",
          520044264,
          "חיפושי נפט וגז",
          "A3",
          "מידרוג",
          "17/08/17",
          3.05,
          "שקל חדש",
          6.0,
          5.49,
          140000.0,
          101.4,
          0.0,
          141.96,
          0.03,
          7.77,
          2.78
        ],
        [
          "אלבר סד יג- אלבר שירותי מימונית בע\"מ",
          1127588,
          "TASE",
          "אחר",
          512025891,
          "שירותים",
          "A3",
          "מידרוג",
          "20/08/14",
          0.89,
          "שקל חדש",
          4.2,
          2.13,
          5156.67,
          103.16,
          0.0,
          5.319620772,
          0.0,
          0.29,
          0.1
        ],
        [
          "דה לסר אגח ד- דה לסר גרופ לימיטד",
          1132059,
          "TASE",
          "אחר",
          1513,
          "נדל\"ן ובינוי",
          "A-",
          "מעלות",
          "10/02/17",
          2.85,
          "שקל חדש",
          2.5,
          4.8,
          35000.0,
          94.17,
          0.0,
          32.9595,
          0.01,
          1.8,
          0.65
        ],
        [
          "דיסקונט השקעות אגח ו- חברת השקעות דיסקונט בע\"מ",
          6390207,
          "TASE",
          "אחר",
          520023896,
          "השקעות ואחזקות",
          "BBB",
          "מעלות",
          "02/04/17",
          3.8,
          "שקל חדש",
          4.95,
          2.77,
          85000.0,
          134.15,
          0.0,
          114.0275,
          0.0,
          6.24,
          2.23
        ],
        [
          "אידיביפת אגח יא- אידיבי חברה לפתוח בע\"מ",
          7980303,
          "TASE",
          "אחר",
          520032285,
          "השקעות ואחזקות",
          "BBB-",
          "מעלות",
          "04/08/16",
          2.07,
          "שקל חדש",
          4.25,
          1.86,
          15790.17,
          105.46,
          0.0,
          16.652313282,
          0.02,
          0.91,
          0.33
        ],
        [
          "כימיקלים לישראל סד ה- כימיקלים לישראל בע\"מ",
          2810299,
          "TASE",
          "אחר",
          520027830,
          "כימיה, גומי ופלסטיק",
          "AA",
          "מעלות",
          "11/04/16",
          4.73,
          "שקל חדש",
          2.45,
          1.75,
          20000.0,
          103.36,
          0.245,
          20.917,
          0.0,
          1.14,
          0.41
        ],
        [
          "וורטון פרופרטיז אגח א",
          1140169,
          "TASE",
          "אחר",
          "",
          "אחר",
          "AA-",
          "מעלות",
          "28/02/17",
          4.02,
          "שקל חדש",
          3.9,
          3.48,
          30000.0,
          102.22,
          0.0,
          30.666,
          0.0,
          1.68,
          0.6
        ],
        [
          "פז נפט אגח ג(ריבית לקבל)- פז חברת הנפט בע\"מ",
          1114073,
          "TASE",
          "אחר",
          510216054,
          "חיפושי נפט וגז",
          "AA-",
          "מעלות",
          "18/09/17",
          1.62,
          "שקל חדש",
          2.3,
          0.76,
          0.0,
          0.0,
          0.0,
          0.2907,
          0.0,
          0.02,
          0.01
        ],
        [
          "קיי.בי.אס הולדינג אגח א- קיי.בי.אס.אס.או.אר(בי.וי.איי)הולדינג אל.טי.די",
          1137918,
          "TASE",
          "אחר",
          1662,
          "נדל\"ן ובינוי",
          "AA-",
          "מעלות",
          "21/07/16",
          3.2,
          "שקל חדש",
          4.25,
          2.76,
          60000.0,
          105.2,
          0.0,
          63.12,
          0.01,
          3.45,
          1.24
        ],
        [
          "נמקו אגח א'- נמקו ריאליטי לטד",
          1139575,
          "TASE",
          "אחר",
          1905761,
          "נדל\"ן ובינוי",
          "A+",
          "מעלות",
          "13/12/16",
          3.62,
          "שקל חדש",
          5.8,
          4.53,
          50000.0,
          106.77,
          0.0,
          53.385,
          0.01,
          2.92,
          1.05
        ],
        [
          "דלק קב   אגח לא- קבוצת דלק בע\"מ",
          1134790,
          "TASE",
          "אחר",
          520044322,
          "השקעות ואחזקות",
          "A",
          "מעלות",
          "20/02/17",
          5.02,
          "שקל חדש",
          4.3,
          2.88,
          40000.0,
          107.85,
          0.0,
          43.14,
          0.0,
          2.36,
          0.85
        ],
        [
          "דלק קבוצה  לג- קבוצת דלק בע\"מ",
          1138882,
          "TASE",
          "אחר",
          520044322,
          "השקעות ואחזקות",
          "A",
          "מעלות",
          "31/07/16",
          4.04,
          "שקל חדש",
          2.8,
          2.5,
          50000.0,
          101.9,
          0.0,
          50.95,
          0.01,
          2.79,
          1.0
        ],
        [
          "ווטרסטון אגח א",
          1140987,
          "TASE",
          "אחר",
          "",
          "נדל\"ן ובינוי",
          "A",
          "מעלות",
          "12/06/17",
          4.21,
          "שקל חדש",
          5.7,
          6.73,
          50000.0,
          98.07,
          0.0,
          49.035,
          0.01,
          2.68,
          0.96
        ],
        [
          "יוניברסל אגח ב- יוניברסל מוטורס  ישראל בע\"מ",
          1141647,
          "TASE",
          "אחר",
          511809071,
          "מסחר",
          "A",
          "מעלות",
          "21/08/17",
          2.82,
          "שקל חדש",
          3.4,
          2.27,
          18181.78,
          103.75,
          0.0,
          18.86359675,
          0.0,
          1.03,
          0.37
        ],
        [
          "ספנסר אגח א- ספנסר אקוויטי גרופ לימיטד",
          1133800,
          "TASE",
          "אחר",
          1838863,
          "נדל\"ן ובינוי",
          "A",
          "מעלות",
          "24/01/17",
          2.86,
          "שקל חדש",
          6.9,
          3.11,
          50000.0,
          113.5,
          0.0,
          56.75,
          0.01,
          3.1,
          1.11
        ],
        [
          "שלמה החזקות אגח טו- ש. שלמה החזקות בע\"מ לשעבר ניו קופל",
          1410273,
          "TASE",
          "אחר",
          520034372,
          "שירותים",
          "A",
          "מעלות",
          "20/08/14",
          1.25,
          "שקל חדש",
          5.75,
          1.03,
          5680.65,
          106.53,
          0.0,
          6.051596445,
          0.0,
          0.33,
          0.12
        ],
        [
          "כנפיים אחזקות אגח ז- כנפיים אחזקות בע\"מ",
          5430137,
          "TASE",
          "אחר",
          520040700,
          "שירותים",
          "A-",
          "מעלות",
          "06/09/16",
          3.64,
          "שקל חדש",
          6.25,
          2.64,
          118491.0,
          113.51,
          18.51422,
          136.200956662,
          0.09,
          7.45,
          2.67
        ],
        [
          "נאוי אגח ב- קבוצת האחים נאוי בע\"מ לשעבר גולדן אקוויטי",
          2080166,
          "TASE",
          "אחר",
          520036070,
          "שירותים פיננסיים",
          "A-",
          "מעלות",
          "18/02/16",
          0.9,
          "שקל חדש",
          2.7,
          1.08,
          20001.0,
          101.71,
          0.0,
          20.3430171,
          0.01,
          1.11,
          0.4
        ],
        [
          "אלדן תחבורה  א- אלדן בע\"מ",
          1134840,
          "TASE",
          "אחר",
          510454333,
          "שירותים",
          "Baa1",
          "מידרוג",
          "10/11/15",
          1.84,
          "שקל חדש",
          4.3,
          2.89,
          12727.2,
          103.03,
          0.0,
          13.11283416,
          0.0,
          0.72,
          0.26
        ],
        [
          "אלדן תחבורה  ב- אלדן בע\"מ",
          1138254,
          "TASE",
          "אחר",
          510454333,
          "שירותים",
          "Baa1",
          "מידרוג",
          "02/11/16",
          2.51,
          "שקל חדש",
          4.25,
          3.16,
          42000.0,
          104.56,
          0.0,
          43.9152,
          0.01,
          2.4,
          0.86
        ],
        [
          "אלון רבוע כחול אגח ד'- אלון החזקות ברבוע כחול- ישראל בע\"מ לשעבר רבוע כחול",
          1139583,
          "TASE",
          "אחר",
          2063,
          "מסחר",
          "Baa1",
          "מידרוג",
          "12/12/16",
          4.46,
          "שקל חדש",
          4.6,
          3.17,
          40000.0,
          107.8,
          0.0,
          43.12,
          0.0,
          2.36,
          0.85
        ],
        [
          "אידיביפת אגח יד- אידיבי חברה לפתוח בע\"מ",
          7980337,
          "TASE",
          "אחר",
          520032285,
          "השקעות ואחזקות",
          "Baa2",
          "מידרוג",
          "24/07/17",
          4.65,
          "שקל חדש",
          5.0,
          5.13,
          50000.0,
          99.87,
          0.46576,
          50.40076,
          0.01,
          2.76,
          0.99
        ],
        [
          "אידיבי פיתוח אגח יב- אידיבי חברה לפתוח בע\"מ",
          7980311,
          "TASE",
          "אחר",
          520032285,
          "השקעות ואחזקות",
          "BBB-",
          "מעלות",
          "23/01/17",
          2.02,
          "שקל חדש",
          6.95,
          2.65,
          70000.0,
          109.7,
          0.0,
          76.79,
          0.02,
          4.2,
          1.5
        ],
        [
          "אידיבי פתוח יג'- אידיבי חברה לפתוח בע\"מ",
          7980329,
          "TASE",
          "אחר",
          520032285,
          "השקעות ואחזקות",
          "BBB-",
          "מעלות",
          "23/02/17",
          2.04,
          "שקל חדש",
          5.4,
          3.63,
          104605.91,
          104.26,
          0.0,
          109.062121766,
          0.01,
          5.97,
          2.14
        ],
        [
          "פטרוכימיים אגח ח- מפעלים פטרוכימיים בישראל בע\"מ",
          7560188,
          "TASE",
          "אחר",
          520029315,
          "כימיה, גומי ופלסטיק",
          0,
          "לא מדורג",
          "11/09/17",
          3.22,
          "שקל חדש",
          6.0,
          6.17,
          25000.0,
          101.6,
          0.0,
          25.4,
          0.01,
          1.39,
          0.5
        ],
        [
          "רציו מימון אגח ב- רציו חיפושי נפט (מימון) בע\"מ",
          1139443,
          "TASE",
          "אחר",
          515060044,
          "חיפושי נפט וגז",
          0,
          "לא מדורג",
          "14/11/16",
          4.65,
          "שקל חדש",
          3.0,
          4.85,
          50000.0,
          114.58,
          0.0,
          57.29,
          0.01,
          3.13,
          1.12
        ],
        [
          "דלק קידוחים אגח א- דלק קידוחים - שותפות מוגבלת",
          4750089,
          "TASE",
          "אחר",
          550013098,
          "חיפושי נפט וגז",
          "A1",
          "מידרוג",
          "19/05/17",
          3.88,
          "שקל חדש",
          4.5,
          4.04,
          60000.0,
          95.41,
          0.0,
          57.246,
          0.0,
          3.13,
          1.12
        ],
        [
          "פורמולה    אג ב- פורמולה מערכות (1985)בע\"מ",
          2560159,
          "TASE",
          "אחר",
          520036690,
          "שירותי מידע",
          "A+",
          "מעלות",
          "17/09/15",
          1.48,
          "שקל חדש",
          2.74,
          -3.17,
          10000.0,
          104.0,
          0.0,
          10.4,
          0.01,
          0.57,
          0.2
        ],
        [
          "חברה לישראל אג\"ח 11- החברה לישראל בע\"מ",
          5760244,
          "TASE",
          "אחר",
          520028010,
          "השקעות ואחזקות",
          "A",
          "מעלות",
          "02/02/17",
          4.15,
          "שקל חדש",
          5.0,
          4.06,
          151000.0,
          98.08,
          0.0,
          148.1008,
          0.01,
          8.1,
          2.9
        ],
        [
          "בזן אגח ו- בתי זקוק לנפט בע\"מ",
          2590396,
          "TASE",
          "אחר",
          520036658,
          "חיפושי נפט וגז",
          "A-",
          "מעלות",
          "21/04/16",
          4.0,
          "שקל חדש",
          6.7,
          4.16,
          25000.0,
          102.48,
          0.0,
          25.62,
          0.0,
          1.4,
          0.5
        ],
        [
          "חלל תקש אגח טז- חלל-תקשורת בע\"מ",
          1139922,
          "TASE",
          "אחר",
          511396046,
          "חיפושי נפט וגז",
          0,
          "לא מדורג",
          "24/01/17",
          5.3,
          "שקל חדש",
          5.95,
          5.8,
          60000.0,
          95.12,
          0.0,
          57.072,
          0.01,
          3.12,
          1.12
        ],
        [
          "devtam 3.839% 30/12/2018- דלק ואבנר תמר בונד בע\"מ",
          "il0011321580",
          "אחר",
          "בלומברג",
          1620,
          "Energy",
          "Baa3",
          "Moodys",
          "12/08/15",
          1.23,
          "דולר אמריקאי",
          3.84,
          2.25,
          8000.0,
          102.613,
          0.0,
          28.96970216,
          0.0,
          1.58,
          0.57
        ]
      ]
    },
    "מניות": {
      "columns": [
        "שם המנפיק/שם נייר ערך",
        "מספר ני\"ע",
        "זירת מסחר",
        "ספק מידע",
        "מספר מנפיק",
        "ענף מסחר",
        "סוג מטבע",
        "ערך נקוב",
        "שער",
        "שווי שוק",
        "שעור מערך נקוב מונפק",
        "שעור מנכסי אפיק ההשקעה",
        "שעור מסך נכסי השקעה"
      ],
      "data": [
        [
          "טבע- טבע תעשיות פרמצבטיות בע\"מ",
          629014,
          "TASE",
          "אחר",
          520013954,
          "ביוטכנולוגיה",
          "שקל חדש",
          650,
          6176.0,
          40.144,
          0,
          8.23,
          0.79
        ],
        [
          "מיילן אן.וי- מיילו אן.וי דואלי",
          1136704,
          "TASE",
          "אחר",
          1655,
          "ביוטכנולוגיה",
          "שקל חדש",
          200,
          11060.0,
          22.12,
          0,
          4.53,
          0.43
        ],
        [
          "פריגו- פריגו קומפני דואלי",
          1130699,
          "TASE",
          "אחר",
          520037599,
          "ביוטכנולוגיה",
          "שקל חדש",
          125,
          29660.0,
          37.075,
          0,
          7.6,
          0.73
        ],
        [
          "אלביט מערכות- אלביט מערכות בע\"מ",
          1081124,
          "TASE",
          "אחר",
          520043027,
          "ביטחוניות",
          "שקל חדש",
          35,
          51930.0,
          18.1755,
          0,
          3.73,
          0.36
        ],
        [
          "דיסקונט א- בנק דיסקונט לישראל בע\"מ",
          691212,
          "TASE",
          "אחר",
          520007030,
          "בנקים",
          "שקל חדש",
          1500,
          891.0,
          13.365,
          0,
          2.74,
          0.26
        ],
        [
          "פועלים- בנק הפועלים בע\"מ",
          662577,
          "TASE",
          "אחר",
          520000118,
          "בנקים",
          "שקל חדש",
          1750,
          2473.0,
          43.2775,
          0,
          8.87,
          0.85
        ],
        [
          "לאומי- בנק לאומי לישראל בע\"מ",
          604611,
          "TASE",
          "אחר",
          520018078,
          "בנקים",
          "שקל חדש",
          3100,
          1875.0,
          58.125,
          0,
          11.92,
          1.14
        ],
        [
          "מזרחי טפחות- בנק מזרחי טפחות בע\"מ",
          695437,
          "TASE",
          "אחר",
          520000522,
          "בנקים",
          "שקל חדש",
          135,
          6333.0,
          8.54955,
          0,
          1.75,
          0.17
        ],
        [
          "בינלאומי 5- הבנק הבינלאומי הראשון לישראל בע\"מ",
          593038,
          "TASE",
          "אחר",
          520029083,
          "בנקים",
          "שקל חדש",
          40,
          6599.0,
          2.6396,
          0,
          0.54,
          0.05
        ],
        [
          "אופקו הלת' אינק- אופקו",
          1129543,
          "TASE",
          "אחר",
          2279206,
          "השקעות במדעי החיים",
          "שקל חדש",
          375,
          2437.0,
          9.13875,
          0,
          1.87,
          0.18
        ],
        [
          "חברה לישראל- החברה לישראל בע\"מ",
          576017,
          "TASE",
          "אחר",
          520028010,
          "השקעות ואחזקות",
          "שקל חדש",
          5,
          70450.0,
          3.5225,
          0,
          0.72,
          0.07
        ],
        [
          "דלק קבוצה- קבוצת דלק בע\"מ",
          1084128,
          "TASE",
          "אחר",
          520044322,
          "השקעות ואחזקות",
          "שקל חדש",
          7,
          66650.0,
          4.6655,
          0,
          0.96,
          0.09
        ],
        [
          "בזן- בתי זקוק לנפט בע\"מ",
          2590248,
          "TASE",
          "אחר",
          520036658,
          "חיפושי נפט וגז",
          "שקל חדש",
          5000,
          176.9,
          8.845,
          0,
          1.81,
          0.17
        ],
        [
          "דלק קדוחים יהש- דלק קידוחים - שותפות מוגבלת",
          475020,
          "TASE",
          "אחר",
          550013098,
          "חיפושי נפט וגז",
          "שקל חדש",
          446,
          1094.0,
          4.87924,
          0,
          1.0,
          0.1
        ],
        [
          "ישראמקו יהש- ישראמקו נגב 2 שותפות מוגבלת",
          232017,
          "TASE",
          "אחר",
          550010003,
          "חיפושי נפט וגז",
          "שקל חדש",
          6050,
          49.1,
          2.97055,
          0,
          0.61,
          0.06
        ],
        [
          "פז נפט- פז חברת הנפט בע\"מ",
          1100007,
          "TASE",
          "אחר",
          510216054,
          "חיפושי נפט וגז",
          "שקל חדש",
          6,
          58210.0,
          3.4926,
          0,
          0.72,
          0.07
        ],
        [
          "כיל- כימיקלים לישראל בע\"מ",
          281014,
          "TASE",
          "אחר",
          520027830,
          "כימיה, גומי ופלסטיק",
          "שקל חדש",
          1400,
          1568.0,
          21.952,
          0,
          4.5,
          0.43
        ],
        [
          "טאואר- טאואר סמיקונדקטור בע\"מ",
          1082379,
          "TASE",
          "אחר",
          520041997,
          "מוליכים למחצה",
          "שקל חדש",
          4,
          10860.0,
          0.4344,
          0,
          0.09,
          0.01
        ],
        [
          "פרוטרום- פרוטרום תעשיות בע\"מ",
          1081082,
          "TASE",
          "אחר",
          520042805,
          "מזון",
          "שקל חדש",
          40,
          27190.0,
          10.876,
          0,
          2.23,
          0.21
        ],
        [
          "שטראוס- שטראוס גרופ בע\"מ",
          746016,
          "TASE",
          "אחר",
          520003781,
          "מזון",
          "שקל חדש",
          45,
          6635.0,
          2.98575,
          0,
          0.61,
          0.06
        ],
        [
          "גזית גלוב- גזית-גלוב בע\"מ",
          126011,
          "TASE",
          "אחר",
          520033234,
          "נדל\"ן ובינוי",
          "שקל חדש",
          120,
          3401.0,
          4.0812,
          0,
          0.84,
          0.08
        ],
        [
          "מליסרון- מליסרון בע\"מ",
          323014,
          "TASE",
          "אחר",
          520037789,
          "נדל\"ן ובינוי",
          "שקל חדש",
          15,
          17090.0,
          2.5635,
          0,
          0.53,
          0.05
        ],
        [
          "עזריאלי קבוצה- קבוצת עזריאלי בע\"מ (לשעבר קנית מימון)",
          1119478,
          "TASE",
          "אחר",
          510960719,
          "נדל\"ן ובינוי",
          "שקל חדש",
          35,
          19620.0,
          6.867,
          0,
          1.41,
          0.13
        ],
        [
          "אורמת טכנולוגיות- אורמת טכנולגיות אינק דואלי",
          1134402,
          "TASE",
          "אחר",
          511597239,
          "קלינטק",
          "שקל חדש",
          25,
          21560.0,
          5.39,
          0,
          1.1,
          0.11
        ],
        [
          "נייס- נייס מערכות בע\"מ",
          273011,
          "TASE",
          "אחר",
          520036872,
          "תוכנה ואינטרנט",
          "שקל חדש",
          85,
          28180.0,
          23.953,
          0,
          4.91,
          0.47
        ],
        [
          "בזק- בזק החברה הישראלית לתקשורת בע\"מ",
          230011,
          "TASE",
          "אחר",
          520031931,
          "תקשורת ומדיה",
          "שקל חדש",
          3500,
          505.1,
          17.6785,
          0,
          3.62,
          0.35
        ],
        [
          "פרטנר- חברת פרטנר תקשורת בע\"מ",
          1083484,
          "TASE",
          "אחר",
          520044314,
          "תקשורת ומדיה",
          "שקל חדש",
          1000,
          1899.0,
          18.99,
          0,
          3.89,
          0.37
        ],
        [
          "מגדל ביטוח- מגדל אחזקות ביטוח ופיננסים בע\"מ",
          1081165,
          "TASE",
          "אחר",
          520029984,
          "ביטוח",
          "שקל חדש",
          380,
          368.4,
          1.39992,
          0,
          0.29,
          0.03
        ],
        [
          "נכסים ובנין- חברה לנכסים ולבנין בע\"מ",
          699017,
          "TASE",
          "אחר",
          520025438,
          "נדל\"ן ובינוי",
          "שקל חדש",
          30,
          32740.0,
          9.822,
          0,
          2.01,
          0.19
        ],
        [
          "סלע נדלן- סלע קפיטל נדל\"ן בע\"מ",
          1109644,
          "TASE",
          "אחר",
          513992529,
          "נדל\"ן ובינוי",
          "שקל חדש",
          4000,
          703.9,
          28.156,
          0,
          5.77,
          0.55
        ],
        [
          "נאוי- קבוצת האחים נאוי בע\"מ לשעבר גולדן אקוויטי",
          208017,
          "TASE",
          "אחר",
          520036070,
          "שירותים פיננסיים",
          "שקל חדש",
          1000,
          1929.0,
          19.29,
          0,
          3.95,
          0.38
        ],
        [
          "בי קומיונקיישנס- בי קומיוניקיישנס בע\"מ לשעבר סמייל 012",
          1107663,
          "TASE",
          "אחר",
          512832742,
          "תקשורת ומדיה",
          "שקל חדש",
          100,
          5043.0,
          5.043,
          0,
          1.03,
          0.1
        ],
        [
          "תמר פטרוליום- תמר פטרוליום בעמ",
          1141357,
          "TASE",
          "אחר",
          515334662,
          "חיפושי נפט וגז",
          "שקל חדש",
          1200,
          2278.0,
          27.336,
          0,
          5.6,
          0.54
        ]
      ]
    },
    "תעודות סל": {
      "columns": [
        "שם המנפיק/שם נייר ערך",
        "מספר ני\"ע",
        "זירת מסחר",
        "מספר מנפיק",
        "ענף מסחר",
        "סוג מטבע",
        "ערך נקוב",
        "שער",
        "פדיון/ ריבית לקבל",
        "שווי שוק",
        "שעור מערך נקוב מונפק",
        "שעור מנכסי אפיק ההשקעה",
        "שעור מסך נכסי השקעה"
      ],
      "data": [
        [
          "פסגות סל ג תא 125- פסגות תעודות סל בע\"מ לשעבר תאלי",
          1096593,
          "TASE",
          512894510,
          "אחר",
          "שקל חדש",
          6750,
          1285.0,
          0,
          86.7375,
          0.0,
          5.24,
          1.7
        ],
        [
          "קסםסמ 33 תא 125- קסם תעודות סל ומוצרי מדדים בע\"מ",
          1117266,
          "TASE",
          513502211,
          "אחר",
          "שקל חדש",
          2500,
          12860.0,
          0,
          321.5,
          0.0,
          19.42,
          6.3
        ],
        [
          "125תכלית סל א ת\"א- תכלית תעודות סל בע\"מ",
          1091818,
          "TASE",
          513594101,
          "אחר",
          "שקל חדש",
          940,
          12850.0,
          0,
          120.79,
          0.0,
          7.29,
          2.37
        ],
        [
          "הראל סל ב' ת\"א 125- הראל סל בע\"מ",
          1113232,
          "TASE",
          514103811,
          "שירותים פיננסיים",
          "שקל חדש",
          13000,
          1287.0,
          0,
          167.31,
          0.01,
          10.1,
          3.28
        ],
        [
          "35פסגות סל ת\"א- פסגות תעודות סל בע\"מ לשעבר תאלי",
          1084656,
          "TASE",
          512894510,
          "שירותים פיננסיים",
          "שקל חדש",
          5000,
          1419.0,
          0,
          70.95,
          0.0,
          4.28,
          1.39
        ],
        [
          "קסם תל אביב 90סמ 31- קסם תעודות סל ומוצרי מדדים בע\"מ",
          1117241,
          "TASE",
          513502211,
          "שירותים פיננסיים",
          "שקל חדש",
          750,
          9620.0,
          0,
          72.15,
          0.0,
          4.36,
          1.41
        ],
        [
          "90תכלית גל ח תא- תכלית גלובל בע\"מ",
          1105386,
          "TASE",
          513815258,
          "שירותים פיננסיים",
          "שקל חדש",
          1280,
          996.5,
          0,
          12.7552,
          0.0,
          0.77,
          0.25
        ],
        [
          "35תכלית סל ב ת\"א- תכלית תעודות סל בע\"מ",
          1091826,
          "TASE",
          513594101,
          "שירותים פיננסיים",
          "שקל חדש",
          8000,
          1416.0,
          0,
          113.28,
          0.0,
          6.84,
          2.22
        ],
        [
          "הראל סל S&P Technology- הראל סל בע\"מ",
          1131796,
          "TASE",
          514103811,
          "אחר",
          "דולר אמריקאי",
          3500,
          2120.0,
          0,
          74.2,
          0.01,
          4.48,
          1.45
        ],
        [
          "הראל סל פד'.MSCI EUROPE FINAC- הראל סל בע\"מ",
          1131788,
          "TASE",
          514103811,
          "אחר",
          "שקל חדש",
          4000,
          1228.0,
          0,
          49.12,
          0.02,
          2.97,
          0.96
        ],
        [
          "תכ.אינדקס.30ש- תכלית אינדקס סל בע\"מ",
          1137579,
          "TASE",
          513801605,
          "אחר",
          "שקל חדש",
          365,
          12610.0,
          0,
          46.0265,
          0.01,
          2.78,
          0.9
        ],
        [
          "תכ. קאק40 ש.  CAC40 מנוטרלת- תכלית גלובל בע\"מ",
          1135649,
          "TASE",
          513815258,
          "אחר",
          "שקל חדש",
          525,
          10220.0,
          0,
          53.655,
          0.01,
          3.24,
          1.05
        ],
        [
          "תכלית נאסדק ביוטכנולוגיה- תכלית תעודות סל בע\"מ",
          1095751,
          "TASE",
          513594101,
          "ביוטכנולוגיה",
          "שקל חדש",
          450,
          10870.0,
          0,
          48.915,
          0.0,
          2.95,
          0.96
        ],
        [
          "הראל סל פ אירופה שח- הראל סל בע\"מ",
          1130376,
          "TASE",
          514103811,
          "שירותים פיננסיים",
          "שקל חדש",
          15000,
          425.6,
          0,
          63.84,
          0.01,
          3.86,
          1.25
        ],
        [
          "פסג מדד נב ראסל- פסגות תעודות סל מדדים בע\"מ",
          1120187,
          "TASE",
          513952457,
          "שירותים פיננסיים",
          "שקל חדש",
          1350,
          5546.0,
          0,
          74.871,
          0.01,
          4.52,
          1.47
        ],
        [
          "פסגות מדד דאקס שח- פסגות תעודות סל מדדים בע\"מ",
          1120203,
          "TASE",
          513952457,
          "שירותים פיננסיים",
          "שקל חדש",
          600,
          12200.0,
          0,
          73.2,
          0.0,
          4.42,
          1.43
        ],
        [
          "פסגות צריכה בסיסי sp- פסגות תעודות סל מדדים בע\"מ",
          1134527,
          "TASE",
          513952457,
          "שירותים פיננסיים",
          "שקל חדש",
          350,
          9064.0,
          0,
          31.724,
          0.01,
          1.92,
          0.62
        ],
        [
          "Mid Cap Euro קסם- קסם תעודות סל ומוצרי מדדים בע\"מ",
          1105550,
          "TASE",
          513502211,
          "שירותים פיננסיים",
          "שקל חדש",
          2000,
          1788.0,
          0,
          35.76,
          0.01,
          2.16,
          0.7
        ],
        [
          "קסם   s&p 500- קסם תעודות סל ומוצרי מדדים בע\"מ",
          1117324,
          "TASE",
          513502211,
          "שירותים פיננסיים",
          "שקל חדש",
          545,
          9019.0,
          0,
          49.15355,
          0.0,
          2.97,
          0.96
        ],
        [
          "קסם גרמניה קנב' MID CAP MDAX מ- קסם תעודות סל ומוצרי מדדים בע\"מ",
          1130731,
          "TASE",
          513502211,
          "שירותים פיננסיים",
          "שקל חדש",
          750,
          2515.0,
          0,
          18.8625,
          0.0,
          1.14,
          0.37
        ],
        [
          "תכלאינ יא ארושח- תכלית אינדקס סל בע\"מ",
          1101823,
          "TASE",
          513801605,
          "שירותים פיננסיים",
          "שקל חדש",
          2000,
          3556.0,
          0,
          71.12,
          0.01,
          4.29,
          1.39
        ]
      ]
    },
    "קרנות נאמנות": {
      "columns": [
        "שם המנפיק/שם נייר ערך",
        "מספר ני\"ע",
        "זירת מסחר",
        "מספר מנפיק",
        "ענף מסחר",
        "דירוג",
        "שם מדרג",
        "סוג מטבע",
        "ערך נקוב",
        "שער",
        "שווי שוק",
        "שעור מערך נקוב מונפק",
        "שעור מנכסי אפיק ההשקעה",
        "שעור מסך נכסי השקעה"
      ],
      "data": [
        [
          "MTF ת\"א 100 קרן נאמנות- מגדל קרנות נאמנות בע\"מ",
          5109889,
          "TASE",
          10308,
          "אחר",
          0,
          "לא מדורג",
          "שקל חדש",
          75000,
          142.78,
          107.085,
          0.02,
          100,
          2.1
        ]
      ]
    },
    "לא סחיר - אג\"ח קונצרני": {
      "columns": [
        "שם המנפיק/שם נייר ערך",
        "מספר ני\"ע",
        "ספק המידע",
        "מספר מנפיק",
        "ענף מסחר",
        "דירוג",
        "שם מדרג",
        "תאריך רכישה",
        "מח\"מ",
        "סוג מטבע",
        "שיעור ריבית",
        "תשואה לפידיון",
        "ערך נקוב",
        "שער",
        "שווי הוגן",
        "שעור מערך נקוב מונפק",
        "שעור מנכסי אפיק ההשקעה",
        "שעור מסך נכסי השקעה"
      ],
      "data": [
        [
          "אליהו הנפ אגח א לס- אליהו חברה לביטוח",
          1142009,
          "אחר",
          11160,
          "השקעות ואחזקות",
          "A1",
          "מידרוג",
          "19/09/17",
          5.47,
          "שקל חדש",
          3.85,
          4.74,
          75000,
          95.71,
          71.7825,
          0.01,
          32.76,
          1.41
        ],
        [
          "ביטוח ישיר אגח יא- ביטוח ישיר - השקעות פיננסיות בע\"מ",
          1138825,
          "אחר",
          520044439,
          "השקעות ואחזקות",
          "A2",
          "מידרוג",
          "10/08/16",
          5.84,
          "שקל חדש",
          4.6,
          3.11,
          84600,
          110.13,
          93.16998,
          0.01,
          42.51,
          1.83
        ],
        [
          "אורמת  סדרה 2 12.09.2016- אורמת טכנולגיות אינק דואלי",
          1139161,
          "אחר",
          511597239,
          "קלינטק",
          "AA-",
          "מעלות",
          "14/09/16",
          2.84,
          "דולר אמריקאי",
          3.7,
          2.92,
          15000,
          102.38,
          54.194853,
          0.02,
          24.73,
          1.06
        ]
      ]
    },
    "לא סחיר - כתבי אופציה": {
      "columns": [
        "שם המנפיק/שם נייר ערך",
        "מספר ני\"ע",
        "ענף מסחר",
        "סוג מטבע",
        "תאריך רכישה",
        "ערך נקוב",
        "שער",
        "שווי הוגן",
        "שעור מערך נקוב מונפק",
        "שעור מנכסי אפיק ההשקעה",
        "שעור מסך נכסי השקעה"
      ],
      "data": [
        [
          "אליהו כתב אופ 1- אליהו חברה לביטוח",
          29992795,
          "השקעות ואחזקות",
          "שקל חדש",
          "28/09/17",
          3075,
          21.693542,
          0.6670764165,
          0,
          23.54,
          0.01
        ],
        [
          "אליהו כתב אופ 2- אליהו חברה לביטוח",
          29992796,
          "השקעות ואחזקות",
          "שקל חדש",
          "28/09/17",
          3075,
          31.141231,
          0.95759285325,
          0,
          33.79,
          0.02
        ],
        [
          "אליהו כתב אופ 3- אליהו חברה לביטוח",
          29992797,
          "השקעות ואחזקות",
          "שקל חדש",
          "28/09/17",
          3075,
          39.328677,
          1.20935681775,
          0,
          42.67,
          0.02
        ]
      ]
    },
    "לא סחיר - מוצרים מובנים": {
      "columns": [
        "שם המנפיק/שם נייר ערך",
        "מספר ני\"ע",
        "נכס הבסיס",
        "דירוג",
        "שם מדרג",
        "תאריך רכישה",
        "מח\"מ",
        "סוג מטבע",
        "שיעור ריבית",
        "תשואה לפידיון",
        "ערך נקוב",
        "שער",
        "שווי הוגן",
        "שעור מערך נקוב מונפק",
        "שעור מנכסי אפיק ההשקעה",
        "שעור מסך נכסי השקעה"
      ],
      "data": [
        [
          "מימון ישיר סידרה 2- מימון ישיר הנפקות  בע\"מ",
          1136035,
          "אשראי",
          "AAA",
          "מעלות",
          "12/08/15",
          1.15,
          "שקל חדש",
          1.95,
          1.28,
          10291.09,
          100.87,
          10.380622483,
          0,
          100,
          0.2
        ]
      ]
    },
    "השקעות אחרות ": {
      "columns": [
        "שם המנפיק/שם נייר ערך",
        "מספר ני\"ע",
        "דירוג",
        "שם המדרג",
        "שעור הריבית",
        "סוג מטבע",
        "תשואה לפדיון",
        "שווי הוגן",
        "שעור מנכסי אפיק ההשקעה",
        "שעור מסך נכסי השקעה"
      ],
      "data": [
        [
          "זכאים מס עמיתים",
          28200000,
          0,
          "לא מדורג",
          0,
          "שקל חדש",
          0,
          -9e-05,
          0.0,
          0.0
        ],
        [
          "חוז חברה מנהלת*",
          28080000,
          0,
          "לא מדורג",
          0,
          "שקל חדש",
          0,
          -2.74035,
          106.42,
          -0.05
        ],
        [
          "חייבים",
          27960000,
          0,
          "לא מדורג",
          0,
          "שקל חדש",
          0,
          0.12334,
          -4.79,
          0.0
        ],
        [
          "גזית גלוב(דיבידנד לקבל)",
          126011,
          0,
          "מעלות",
          0,
          "שקל חדש",
          0,
          0.042,
          -1.63,
          0.0
        ]
      ]
    }
  }
}